cx_Logging.cp39-win32.pyd
cx_Logging-3.2.1.data/data/include/cx_Logging.h
cx_Logging-3.2.1.data/data/libs/cx_Logging.lib
cx_Logging-3.2.1.dist-info/LICENSE.txt
cx_Logging-3.2.1.dist-info/METADATA
cx_Logging-3.2.1.dist-info/WHEEL
cx_Logging-3.2.1.dist-info/top_level.txt
cx_Logging-3.2.1.dist-info/RECORD
