Metadata-Version: 2.1
Name: cx_Logging
Version: 3.2.1
Summary: Python and C interfaces for logging
Author-email: Anthony Tuininga <anthony.tuininga@gmail.com>
License: BSD License
Project-URL: Homepage, https://github.com/anthony-tuininga/cx_Logging
Keywords: logging
Classifier: Development Status :: 5 - Production/Stable
Classifier: Intended Audience :: Developers
Classifier: License :: OSI Approved :: BSD License
Classifier: Natural Language :: English
Classifier: Operating System :: OS Independent
Classifier: Programming Language :: C
Classifier: Programming Language :: Python
Classifier: Topic :: Software Development :: Libraries :: Python Modules
Classifier: Topic :: Utilities
Requires-Python: >=3.9
License-File: LICENSE.txt
